streamlink_repo/__init__.py
streamlink_repo/common.py
streamlink_repo/paths.py
streamlink_repo-1.0.5.dist-info/LICENSE
streamlink_repo-1.0.5.dist-info/METADATA
streamlink_repo-1.0.5.dist-info/WHEEL
streamlink_repo-1.0.5.dist-info/entry_points.txt
streamlink_repo-1.0.5.dist-info/top_level.txt
streamlink_repo-1.0.5.dist-info/RECORD
