Metadata-Version: 2.1
Name: streamlink-repo
Version: 1.0.5
Summary: Unofficial Plugin repository implementation for streamlink-cli.
Author: Parrot Developers
License-File: LICENSE
Requires-Dist: pyinquirer
Requires-Dist: colorama
Requires-Dist: tqdm
Requires-Dist: typer
